{
  "field": {
    "ra": 185.0,
    "dec": 50.0,
    "radius_deg": 1.0
  },
  "band": "r",
  "variable_only": true,
  "n_searched": 3414,
  "n_candidates": 3,
  "n_resists_mundane": 2,
  "n_secular_faders": 47,
  "top_faders": [
    {
      "source_id": "755210200003810",
      "ra": 186.14519475,
      "dec": 49.19058795,
      "secular_slope_mag_yr": 0.08408936165468331,
      "secular_sigma": 11.52982295551714,
      "secular_total_mag": 0.34188653478253,
      "hr_class": "unknown"
    },
    {
      "source_id": "755210200004199",
      "ra": 185.7751655,
      "dec": 49.1546999,
      "secular_slope_mag_yr": 0.15147865409503242,
      "secular_sigma": 11.442154689399265,
      "secular_total_mag": 0.45991757616294504,
      "hr_class": "unknown"
    },
    {
      "source_id": "755211200004602",
      "ra": 184.05212655,
      "dec": 49.1273659,
      "secular_slope_mag_yr": 0.1273014862559049,
      "secular_sigma": 8.98233376825446,
      "secular_total_mag": 0.379058402686607,
      "hr_class": "unknown"
    },
    {
      "source_id": "755211200004422",
      "ra": 183.4546746,
      "dec": 49.1337644,
      "secular_slope_mag_yr": 0.1684908826294474,
      "secular_sigma": 8.722548198781526,
      "secular_total_mag": 0.49314634885524655,
      "hr_class": "unknown"
    },
    {
      "source_id": "755211100029672",
      "ra": 184.94252310000002,
      "dec": 49.1271617,
      "secular_slope_mag_yr": 0.104060525394728,
      "secular_sigma": 7.7977525318124155,
      "secular_total_mag": 0.3080014378133695,
      "hr_class": "unknown"
    },
    {
      "source_id": "755210200005513",
      "ra": 185.79661555,
      "dec": 49.0308977,
      "secular_slope_mag_yr": 0.10021638559317834,
      "secular_sigma": 7.7238949297145325,
      "secular_total_mag": 0.3951188769079412,
      "hr_class": "unknown"
    },
    {
      "source_id": "755210200013364",
      "ra": 185.7397994,
      "dec": 49.07820705,
      "secular_slope_mag_yr": 0.057070366192955864,
      "secular_sigma": 7.463231611810173,
      "secular_total_mag": 0.27781704468058693,
      "hr_class": "unknown"
    },
    {
      "source_id": "755211200024276",
      "ra": 183.5232082,
      "dec": 49.1999244,
      "secular_slope_mag_yr": 0.0810896069819907,
      "secular_sigma": 7.2256985813847985,
      "secular_total_mag": 0.31017925841095273,
      "hr_class": "unknown"
    },
    {
      "source_id": "755211100004028",
      "ra": 185.2492095,
      "dec": 49.1896833,
      "secular_slope_mag_yr": 0.12245913429829901,
      "secular_sigma": 7.213039420385607,
      "secular_total_mag": 0.36447023632354025,
      "hr_class": "unknown"
    },
    {
      "source_id": "755211200004566",
      "ra": 183.6773293,
      "dec": 49.1246327,
      "secular_slope_mag_yr": 0.06639752684433617,
      "secular_sigma": 7.064780271354605,
      "secular_total_mag": 0.25624351656327193,
      "hr_class": "unknown"
    },
    {
      "source_id": "755211200004977",
      "ra": 183.7124073,
      "dec": 49.0896118,
      "secular_slope_mag_yr": 0.25809982373969986,
      "secular_sigma": 6.836916004679631,
      "secular_total_mag": 0.7875994644887636,
      "hr_class": "unknown"
    },
    {
      "source_id": "755211200038813",
      "ra": 183.5239245,
      "dec": 49.1226086,
      "secular_slope_mag_yr": 0.22255160209038172,
      "secular_sigma": 6.508702486237452,
      "secular_total_mag": 0.6836452619016496,
      "hr_class": "unknown"
    },
    {
      "source_id": "755211100005339",
      "ra": 185.05626795,
      "dec": 49.06458605,
      "secular_slope_mag_yr": 0.10424212591364311,
      "secular_sigma": 6.374493184758837,
      "secular_total_mag": 0.311096061814665,
      "hr_class": "unknown"
    },
    {
      "source_id": "755211100004346",
      "ra": 184.6994096,
      "dec": 49.1574533,
      "secular_slope_mag_yr": 0.04310530758890419,
      "secular_sigma": 6.168079005936306,
      "secular_total_mag": 0.30614551483170777,
      "hr_class": "unknown"
    },
    {
      "source_id": "755210200005250",
      "ra": 186.0725528,
      "dec": 49.0543367,
      "secular_slope_mag_yr": 0.09539627349949158,
      "secular_sigma": 6.141806743591171,
      "secular_total_mag": 0.3736370626196294,
      "hr_class": "unknown"
    },
    {
      "source_id": "755211100039099",
      "ra": 184.8918506,
      "dec": 49.166540850000004,
      "secular_slope_mag_yr": 0.019420220268245626,
      "secular_sigma": 6.087203676381856,
      "secular_total_mag": 0.13792803226908573,
      "hr_class": "unknown"
    },
    {
      "source_id": "755211100013334",
      "ra": 184.74737855,
      "dec": 49.10187445,
      "secular_slope_mag_yr": 0.11942726230716899,
      "secular_sigma": 5.911782043690744,
      "secular_total_mag": 0.34563632386750526,
      "hr_class": "unknown"
    },
    {
      "source_id": "755211200013305",
      "ra": 183.4819845,
      "dec": 49.0740256,
      "secular_slope_mag_yr": 0.12276579349084625,
      "secular_sigma": 5.881072651677835,
      "secular_total_mag": 0.37560171877856546,
      "hr_class": "unknown"
    },
    {
      "source_id": "755211200004248",
      "ra": 183.92640484999998,
      "dec": 49.16019745,
      "secular_slope_mag_yr": 0.15891207679387231,
      "secular_sigma": 5.596895507112516,
      "secular_total_mag": 0.6280780206823049,
      "hr_class": "unknown"
    },
    {
      "source_id": "755211200005807",
      "ra": 183.9824564,
      "dec": 49.0079761,
      "secular_slope_mag_yr": 0.14359519743932134,
      "secular_sigma": 5.59200103700857,
      "secular_total_mag": 0.4328827148843589,
      "hr_class": "unknown"
    }
  ],
  "selection": {
    "depth_min": 0.1,
    "n_dips_min": 3,
    "asym_min": 1.5,
    "period_power_max": 0.4
  },
  "top_candidates": [
    {
      "source_id": "755211200004560",
      "ra": 183.564229,
      "dec": 49.1233848,
      "score": 0.9572472615339508,
      "max_depth": 0.8164167660485581,
      "n_dips": 33,
      "n_dip_events": 5,
      "max_event_depth": 0.7482060006323037,
      "out_of_dip_rms": 0.0,
      "asymmetry": 6.67025936603999,
      "best_period_d": 1.0012968601848637,
      "period_power": 0.042509128220164026,
      "hr_class": "main_sequence",
      "resists_mundane": true
    },
    {
      "source_id": "755211200005068",
      "ra": 183.5477878,
      "dec": 49.0769576,
      "score": 0.7698048915454362,
      "max_depth": 0.654871932242532,
      "n_dips": 11,
      "n_dip_events": 1,
      "max_event_depth": 0.5069197131055649,
      "out_of_dip_rms": 0.0,
      "asymmetry": 2.8288227117034537,
      "best_period_d": 0.9994752060573188,
      "period_power": 0.03308157052257014,
      "hr_class": "main_sequence",
      "resists_mundane": true
    },
    {
      "source_id": "755211200004337",
      "ra": 183.5422616,
      "dec": 49.14473135,
      "score": 0.49981803140161607,
      "max_depth": 0.8591444512194104,
      "n_dips": 19,
      "n_dip_events": 1,
      "max_event_depth": 0.107947037182626,
      "out_of_dip_rms": 0.0,
      "asymmetry": 1.746850112106902,
      "best_period_d": 0.22325164173414588,
      "period_power": 0.0211319764625011,
      "hr_class": "unknown",
      "resists_mundane": false
    }
  ],
  "occurrence_limit": {
    "k_candidates": 3,
    "n_eff": 3414.0,
    "confidence": 0.95,
    "f_upper": 0.0022711354797693983,
    "f_point": 0.0008787346221441124
  }
}